{
   "method_id":1693,
   "method_url":"/events.{format}",
   "method_name":"get_global_events",
   "service_id":271,
   "service_name":"events",
   "request_protocol":"GET",
   "is_authenticated":false,
   "is_enabled": true,
   "update_frequency":"Realtime",
   "cache_time_s":0,
   "data_type":"Database",
   "data_source":[
    "Crawled from all WMCS sites listed at https://api.uwaterloo.ca/v2/resources/sites.{format}"
   ],
   "method_description":[
       "This method returns a list of the upcomming 21 University of Waterloo events as crawled from all University WCMS sites"
   ],
   "additional_notes":[
       "This is a 'realtime' feed. An item will be available on the api the second its up using Webhooks",
       "```description``` and ```description_raw``` is only returned when passing in ```id```"
   ],
   "information_steward":"UW API",
   "request_examples":[
      "https://api.uwaterloo.ca/v2/events/22.json",
      "https://api.uwaterloo.ca/v2/events.json",
      "https://api.uwaterloo.ca/v2/events.xml",
      "https://api.uwaterloo.ca/v2/events.json?callback=myResponse"
   ],
   "response_formats":[
      "json",
      "xml"
   ],
   "method_parameters":[
       {
         "parameter":"key",
         "description":"Valid API key",
         "is_required":true,
         "type":"filter"
      },
      {
         "parameter":"id",
         "description":"Valid event id",
         "is_required":false,
         "type":"filter"
      },
      {
         "parameter":"callback",
         "description":"JSONP callback format",
         "is_required":false,
         "type":"filter"
      }
   ],
   "response_fields":[
      {
         "field":"id",
         "description":"Unique event id",
         "type":"integer"
      },
      {
         "field":"title",
         "description":"event title",
         "type":"string"
      },
      {
         "field":"location",
         "description":"Description of location in free format",
         "type":"string"
      },
      {
         "field":"start",
         "description":"ISO 8601 formatted start date",
         "type":"date"
      },
      {
         "field":"end",
         "description":"ISO 8601 formatted end date",
         "type":"date"
      },
      {
         "field":"description",
         "description":"Event description",
         "type":"string"
      },
      {
         "field":"description_raw",
         "description":"Raw event description",
         "type":"string"
      },
      {
         "field":"categories",
         "description":"Tags of all related categories",
         "type":"array"
      },
      {
         "field":"updated",
         "description":"ISO 8601 formatted updated date",
         "type":"date"
      },
      {
         "field":"url",
         "description":"URL of event link",
         "type":"string"
      }
   ]
}
